log2mongo/__init__.py
log2mongo/mongo_logger.py
log2mongo/mongodb_service.py
log2mongo-0.1.0.dist-info/licenses/LICENSE
log2mongo-0.1.0.dist-info/METADATA
log2mongo-0.1.0.dist-info/WHEEL
log2mongo-0.1.0.dist-info/top_level.txt
log2mongo-0.1.0.dist-info/RECORD
