Metadata-Version: 2.4
Name: log2mongo
Version: 0.1.0
Summary: A small example package
Author: ablogo
License-Expression: GPL-3.0-only
Project-URL: Homepage, https://github.com/ablogo/
Classifier: Programming Language :: Python :: 3
Classifier: Operating System :: OS Independent
Requires-Python: >=3.12
License-File: LICENSE
Dynamic: license-file
